README.rst
setup.py
lastpass/__init__.py
lastpass/account.py
lastpass/blob.py
lastpass/chunk.py
lastpass/exceptions.py
lastpass/fetcher.py
lastpass/parser.py
lastpass/session.py
lastpass/vault.py
lastpass/version.py
lastpass_python.egg-info/PKG-INFO
lastpass_python.egg-info/SOURCES.txt
lastpass_python.egg-info/dependency_links.txt
lastpass_python.egg-info/requires.txt
lastpass_python.egg-info/top_level.txt