Metadata-Version: 1.1
Name: lastpass-python
Version: 0.3.2
Summary: Read only access to the online LastPass vault (unofficial)
Home-page: https://github.com/konomae/lastpass-python
Author: konomae
Author-email: konomae@users.noreply.github.com
License: MIT
Platform: UNKNOWN
Classifier: Development Status :: 3 - Alpha
Classifier: License :: OSI Approved :: MIT License
Classifier: Intended Audience :: Developers
Classifier: Programming Language :: Python
Classifier: Programming Language :: Python :: 2
Classifier: Programming Language :: Python :: 2.7
Classifier: Programming Language :: Python :: 3
Classifier: Programming Language :: Python :: 3.6
Classifier: Programming Language :: Python :: Implementation :: CPython
